{"id":"324473","name":"Faventia","promotions":[]}
{"id":"33786","name":"Le 1947","promotions":[]}
{"id":"6018","name":"Le Vieux Logis","promotions":[]}
{"id":"28558","name":"Le Gourmet de Sèze","promotions":[]}
{"id":"323145","name":"Le Passe Temps","promotions":[]}
{"id":"4294","name":"La Maison dans le Parc","promotions":[]}
{"id":"23303","name":"La Table de Nans","promotions":[]}
{"id":"14529","name":"La Chassagnette","promotions":[]}
{"id":"4546","name":"Auberge des Saints Pères","promotions":[]}
{"id":"344379","name":"Astrance","promotions":[]}
{"id":"7876","name":"Mon Plaisir","promotions":[]}
{"id":"326081","name":"L'Écrin","promotions":[]}
{"id":"28557","name":"La Grange de Belle-Église","promotions":[]}
{"id":"313905","name":"Auberge Le Prieuré","promotions":[]}
{"id":"44919","name":"Miraflores","promotions":[]}
{"id":"4977","name":"Le Saint-James","promotions":[]}
{"id":"11743","name":"Brikéténia","promotions":[]}
{"id":"337449","name":"Comice","promotions":[]}
{"id":"6482","name":"Vieux Pont","promotions":[]}
{"id":"26660","name":"La Vague d'Or","promotions":[]}
{"id":"8719","name":"Ô Saveurs","promotions":[]}
{"id":"27058","name":"Initial","promotions":[]}
{"id":"63173","name":"Fontevraud Le Restaurant","promotions":[]}
{"id":"3592","name":"Buerehiesel","promotions":[]}
{"id":"77571","name":"La Table de Manville","promotions":[]}
{"id":"9759","name":"Le Carrousel","promotions":[]}
{"id":"10427","name":"Les Morainières","promotions":[]}
{"id":"35732","name":"Anne de Bretagne","promotions":[]}
{"id":"46990","name":"Rackham","promotions":[]}
{"id":"6448","name":"Les Bacchanales","promotions":[]}
{"id":"5623","name":"Le Corot","promotions":[]}
{"id":"22878","name":"Domaine de Clairefontaine","promotions":[]}
{"id":"3131","name":"Gordon Ramsay au Trianon","promotions":[]}
{"id":"2579","name":"Auberge de la Charme","promotions":[]}
{"id":"61705","name":"Le Camélia","promotions":[]}
{"id":"6792","name":"Le Domaine de la Corniche","promotions":[]}
{"id":"26494","name":"La Barbacane","promotions":[]}
{"id":"46885","name":"Le Gambetta","promotions":[]}
{"id":"3304","name":"Loiseau des Vignes","promotions":[]}
{"id":"3157","name":"Gill","promotions":[]}
{"id":"7130","name":"Le Clos des Sens","promotions":[]}
{"id":"24998","name":"Restaurant des Rois","promotions":[]}
{"id":"2788","name":"La Villa Madie","promotions":[]}
{"id":"75043","name":"Prairial","promotions":[]}
{"id":"11295","name":"Qui plume la Lune","promotions":[]}
{"id":"209577","name":"Restaurant H","promotions":[]}
{"id":"9228","name":"Le Baudelaire","promotions":[]}
{"id":"12900","name":"Pierre Orsi","promotions":[]}
{"id":"5497","name":"La Scène","promotions":[]}
{"id":"6765","name":"Auberge de la Diligence","promotions":[]}
{"id":"60859","name":"Nakatani","promotions":[]}
{"id":"6710","name":"Les Rosiers","promotions":[]}
{"id":"38154","name":"L'Aromate","promotions":[]}
{"id":"206163","name":"Julien Binz","promotions":[]}
{"id":"25896","name":"Benoit","promotions":[]}
{"id":"291345","name":"114, Faubourg","promotions":[]}
{"id":"221","name":"Le France","promotions":[]}
{"id":"5649","name":"La Grand'Vigne","promotions":[]}
{"id":"5487","name":"Château de Mirambeau","promotions":[]}
{"id":"7872","name":"Le Pavillon des Boulevards","promotions":[]}
{"id":"30315","name":"Les Climats","promotions":[]}
{"id":"58408","name":"La Table du 11","promotions":[]}
{"id":"53046","name":"Sur Mesure par Thierry Marx","promotions":[]}
{"id":"250","name":"Lasserre","promotions":[]}
{"id":"1226","name":"Le Figuier de St-Esprit","promotions":[]}
{"id":"11050","name":"Le Cloître","promotions":[]}
{"id":"60418","name":"Apicius","promotions":[]}
{"id":"3931","name":"William Frachot","promotions":[]}
{"id":"69375","name":"Au Trou Gascon","promotions":[]}
{"id":"2970","name":"La Renaissance","promotions":[]}
{"id":"27598","name":"Les Bories","promotions":[]}
{"id":"713","name":"L'Arôme","promotions":[]}
{"id":"330375","name":"Le Village","promotions":[]}
{"id":"1086","name":"Le Vivier","promotions":[]}
{"id":"132","name":"Le Relais des Moines","promotions":[]}
{"id":"6794","name":"Mère Brazier","promotions":[]}
{"id":"5355","name":"Paul Bocuse","promotions":[]}
{"id":"19211","name":"1741","promotions":[]}
{"id":"7715","name":"Terre-Mer","promotions":[]}
{"id":"74933","name":"Le Clarence","promotions":[]}
{"id":"387","name":"Le Mascaret","promotions":[]}
{"id":"69372","name":"Carré des Feuillants","promotions":[]}
{"id":"378","name":"Ithurria","promotions":[]}
{"id":"10382","name":"Le Strasbourg","promotions":[]}
{"id":"202436","name":"Le Chateaubriand","promotions":[]}
{"id":"324425","name":"Le Neuvième Art","promotions":[]}
{"id":"26327","name":"Elsa","promotions":[]}
{"id":"44000","name":"Logis de la Cadène","promotions":[]}
{"id":"201032","name":"1920","promotions":[]}
{"id":"5632","name":"La Licorne Royale","promotions":[]}
{"id":"205419","name":"La Dame de Pic","promotions":[]}
{"id":"6437","name":"L'Atelier du Peintre","promotions":[]}
{"id":"43399","name":"La Grignotière","promotions":[]}
{"id":"310489","name":"Laurent","promotions":[]}
{"id":"26112","name":"Le 39V","promotions":[]}
{"id":"5603","name":"JY'S","promotions":[]}
{"id":"18188","name":"Le Pressoir","promotions":[]}
{"id":"5619","name":"Stéphane Derbord","promotions":[]}
{"id":"2698","name":"Jean-Luc Tartarin","promotions":[]}
{"id":"36039","name":"Hélène Darroze","promotions":[]}
{"id":"13311","name":"Château de Mercuès","promotions":[]}
{"id":"5609","name":"Chapelle Saint-Martin","promotions":[]}
{"id":"7135","name":"Les Trois Rochers","promotions":[]}
{"id":"77134","name":"Mickaël Féval","promotions":[]}
{"id":"2819","name":"Les Hautes Roches","promotions":[]}
{"id":"8685","name":"Villa Archange","promotions":[]}
{"id":"57531","name":"La Bastide de Moustiers","promotions":[]}
{"id":"1310","name":"Xavier Mathieu","promotions":[]}
{"id":"122","name":"La Grande Cascade","promotions":[]}
{"id":"31008","name":"Alcyone","promotions":[]}
{"id":"29826","name":"Loiseau des Ducs","promotions":[]}
{"id":"4697","name":"Les Terrasses de Lyon","promotions":[]}
{"id":"21095","name":"Jérémy Galvan","promotions":[]}
{"id":"1009","name":"Domaine des Séquoias","promotions":[]}
{"id":"25985","name":"Copenhague","promotions":[]}
{"id":"2185","name":"Antoine","promotions":[]}
{"id":"269585","name":"La Scène Thélème","promotions":[]}
{"id":"23454","name":"Helen","promotions":[]}
{"id":"2591","name":"La Table des Merville","promotions":[]}
{"id":"26352","name":"Le Moulin de l'Abbaye","promotions":[]}
{"id":"8933","name":"Les Clefs d'Argent","promotions":[]}
{"id":"347931","name":"SEPT","promotions":[]}
{"id":"23087","name":"Frédéric Simonin","promotions":[]}
{"id":"18939","name":"Le Bistro des Saveurs","promotions":[]}
{"id":"3507","name":"Hostellerie de Levernois","promotions":[]}
{"id":"8628","name":"Le Park 45","promotions":[]}
{"id":"291337","name":"Épicure","promotions":[]}
{"id":"2934","name":"Auberge du Bon Laboureur","promotions":[]}
{"id":"7133","name":"Le Moulin du Roc","promotions":[]}
{"id":"689","name":"Le Prieuré","promotions":[]}
{"id":"2975","name":"La Table du Gourmet","promotions":[]}
{"id":"204609","name":"Le Castellaras","promotions":[]}
{"id":"42187","name":"La Promenade","promotions":[]}
{"id":"8760","name":"Saturne","promotions":[]}
{"id":"24998","name":"Restaurant des Rois","promotions":[]}
{"id":"60775","name":"La Table du Connétable","promotions":[]}
{"id":"14529","name":"La Chassagnette","promotions":[]}
{"id":"58408","name":"La Table du 11","promotions":[]}
{"id":"33786","name":"Le 1947","promotions":[]}
{"id":"25985","name":"Copenhague","promotions":[]}
{"id":"326081","name":"L'Écrin","promotions":[]}
{"id":"4546","name":"Auberge des Saints Pères","promotions":[]}
{"id":"75043","name":"Prairial","promotions":[]}
{"id":"35732","name":"Anne de Bretagne","promotions":[]}
{"id":"63173","name":"Fontevraud Le Restaurant","promotions":[]}
{"id":"26327","name":"Elsa","promotions":[]}
{"id":"6018","name":"Le Vieux Logis","promotions":[]}
{"id":"324473","name":"Faventia","promotions":[]}
{"id":"1086","name":"Le Vivier","promotions":[]}
{"id":"77571","name":"La Table de Manville","promotions":[]}
{"id":"206163","name":"Julien Binz","promotions":[]}
{"id":"11295","name":"Qui plume la Lune","promotions":[]}
{"id":"344379","name":"Astrance","promotions":[]}
{"id":"5727","name":"Mavrommatis","promotions":[]}
{"id":"22878","name":"Domaine de Clairefontaine","promotions":[]}
{"id":"7130","name":"Le Clos des Sens","promotions":[]}
{"id":"27058","name":"Initial","promotions":[]}
{"id":"323145","name":"Le Passe Temps","promotions":[]}
{"id":"5632","name":"La Licorne Royale","promotions":[]}
{"id":"9759","name":"Le Carrousel","promotions":[]}
{"id":"291345","name":"114, Faubourg","promotions":[]}
{"id":"3592","name":"Buerehiesel","promotions":[]}
{"id":"32584","name":"L'Auberge de la Pomme","promotions":[]}
{"id":"21095","name":"Jérémy Galvan","promotions":[]}
{"id":"32118","name":"Le Musigny","promotions":[]}
{"id":"28557","name":"La Grange de Belle-Église","promotions":[]}
{"id":"10427","name":"Les Morainières","promotions":[]}
{"id":"23303","name":"La Table de Nans","promotions":[]}
{"id":"6482","name":"Vieux Pont","promotions":[]}
{"id":"5497","name":"La Scène","promotions":[]}
{"id":"250","name":"Lasserre","promotions":[]}
{"id":"3507","name":"Hostellerie de Levernois","promotions":[]}
{"id":"529","name":"Le Puits du Trésor","promotions":[]}
{"id":"35146","name":"L'Atelier de Joël Robuchon - Étoile","promotions":[]}
{"id":"61705","name":"Le Camélia","promotions":[]}
{"id":"7876","name":"Mon Plaisir","promotions":[]}
{"id":"53038","name":"Le Gabriel","promotions":[]}
{"id":"2819","name":"Les Hautes Roches","promotions":[]}
{"id":"2971","name":"Maison Kieny","promotions":[]}
{"id":"269931","name":"Les Jardins de l'Espadon","promotions":[]}
{"id":"4294","name":"La Maison dans le Parc","promotions":[]}
{"id":"209577","name":"Restaurant H","promotions":[]}
{"id":"46721","name":"Neige d'Été","promotions":[]}
{"id":"46990","name":"Rackham","promotions":[]}
{"id":"10889","name":"Septime","promotions":[]}
{"id":"38024","name":"La Nouvelle Auberge","promotions":[]}
{"id":"297223","name":"Le Restaurant","promotions":[]}
{"id":"11050","name":"Le Cloître","promotions":[]}
{"id":"5109","name":"Le Magasin aux Vivres","promotions":[]}
{"id":"2755","name":"Auberge de Clochemerle","promotions":[]}
{"id":"60418","name":"Apicius","promotions":[]}
{"id":"6794","name":"Mère Brazier","promotions":[]}
{"id":"5619","name":"Stéphane Derbord","promotions":[]}
{"id":"5305","name":"L'Auberge Basque","promotions":[]}
{"id":"8933","name":"Les Clefs d'Argent","promotions":[]}
{"id":"13311","name":"Château de Mercuès","promotions":[]}
{"id":"291337","name":"Épicure","promotions":[]}
{"id":"31008","name":"Alcyone","promotions":[]}
{"id":"203823","name":"La Passagère","promotions":[]}
{"id":"310489","name":"Laurent","promotions":[]}
{"id":"10332","name":"Le Refuge des Gourmets","promotions":[]}
{"id":"8838","name":"Henri et Joseph","promotions":[]}
{"id":"9228","name":"Le Baudelaire","promotions":[]}
{"id":"8977","name":"Shang Palace","promotions":[]}
{"id":"25701","name":"Garance","promotions":[]}
{"id":"12601","name":"Le Cerf","promotions":[]}
{"id":"7135","name":"Les Trois Rochers","promotions":[]}
{"id":"44361","name":"Auberge au Boeuf","promotions":[]}
{"id":"18939","name":"Le Bistro des Saveurs","promotions":[]}
{"id":"2975","name":"La Table du Gourmet","promotions":[]}
{"id":"3131","name":"Gordon Ramsay au Trianon","promotions":[]}
{"id":"347931","name":"SEPT","promotions":[]}
{"id":"689","name":"Le Prieuré","promotions":[]}
{"id":"2970","name":"La Renaissance","promotions":[]}
{"id":"27598","name":"Les Bories","promotions":[]}
{"id":"28558","name":"Le Gourmet de Sèze","promotions":[]}
{"id":"71542","name":"Au Crocodile","promotions":[]}
{"id":"5487","name":"Château de Mirambeau","promotions":[]}
{"id":"313905","name":"Auberge Le Prieuré","promotions":[]}
{"id":"713","name":"L'Arôme","promotions":[]}
{"id":"1310","name":"Xavier Mathieu","promotions":[]}
{"id":"2889","name":"La Marande","promotions":[]}
{"id":"30379","name":"Jin","promotions":[]}
{"id":"284489","name":"L'Archeste","promotions":[]}
{"id":"11743","name":"Brikéténia","promotions":[]}
{"id":"2579","name":"Auberge de la Charme","promotions":[]}
{"id":"291883","name":"La Table de l'Alpaga","promotions":[]}
{"id":"5020","name":"La Fourchette du Printemps","promotions":[]}
{"id":"2998","name":"Christopher Coutanceau","promotions":[]}
{"id":"19211","name":"1741","promotions":[]}
{"id":"31795","name":"Auberge du Vert Mont","promotions":[]}
{"id":"44000","name":"Logis de la Cadène","promotions":[]}
{"id":"15413","name":"Les Trois Dômes","promotions":[]}
{"id":"1226","name":"Le Figuier de St-Esprit","promotions":[]}
{"id":"8628","name":"Le Park 45","promotions":[]}
{"id":"4977","name":"Le Saint-James","promotions":[]}
{"id":"18271","name":"Le Clair de la Plume","promotions":[]}
{"id":"3997","name":"Têtedoie","promotions":[]}
{"id":"44919","name":"Miraflores","promotions":[]}
{"id":"4904","name":"Hostellerie de Plaisance","promotions":[]}
{"id":"30315","name":"Les Climats","promotions":[]}
{"id":"330375","name":"Le Village","promotions":[]}
{"id":"36884","name":"La Table d'Eugène","promotions":[]}
{"id":"73961","name":"Le George","promotions":[]}
{"id":"6792","name":"Le Domaine de la Corniche","promotions":[]}
{"id":"387","name":"Le Mascaret","promotions":[]}
{"id":"12601","name":"Le Cerf","promotions":[]}
{"id":"1310","name":"Xavier Mathieu","promotions":[]}
{"id":"206163","name":"Julien Binz","promotions":[]}
{"id":"63173","name":"Fontevraud Le Restaurant","promotions":[]}
{"id":"22878","name":"Domaine de Clairefontaine","promotions":[]}
{"id":"19211","name":"1741","promotions":[]}
{"id":"3131","name":"Gordon Ramsay au Trianon","promotions":[]}
{"id":"205419","name":"La Dame de Pic","promotions":[]}
{"id":"7876","name":"Mon Plaisir","promotions":[]}
{"id":"71542","name":"Au Crocodile","promotions":[]}
{"id":"27058","name":"Initial","promotions":[]}
{"id":"75533","name":"La Tour des Vents","promotions":[]}
{"id":"46885","name":"Le Gambetta","promotions":[]}
{"id":"1009","name":"Domaine des Séquoias","promotions":[]}
{"id":"26494","name":"La Barbacane","promotions":[]}
{"id":"44919","name":"Miraflores","promotions":[]}
{"id":"11743","name":"Brikéténia","promotions":[]}
{"id":"7135","name":"Les Trois Rochers","promotions":[]}
{"id":"75043","name":"Prairial","promotions":[]}
{"id":"26460","name":"Ivan Vautier","promotions":[]}
{"id":"6986","name":"Alexandre","promotions":[]}
{"id":"3401","name":"Le Bec au Cauchois","promotions":[]}
{"id":"566","name":"L'Almandin","promotions":[]}
{"id":"5020","name":"La Fourchette du Printemps","promotions":[]}
{"id":"713","name":"L'Arôme","promotions":[]}
{"id":"301377","name":"Le Chantecler","promotions":[]}
{"id":"21632","name":"L'Essentiel","promotions":[]}
{"id":"785","name":"Lucas Carton","promotions":[]}
{"id":"416","name":"Hostellerie Bérard","promotions":[]}
{"id":"13311","name":"Château de Mercuès","promotions":[]}
{"id":"291883","name":"La Table de l'Alpaga","promotions":[]}
{"id":"63173","name":"Fontevraud Le Restaurant","promotions":[]}
{"id":"33786","name":"Le 1947","promotions":[]}
{"id":"69375","name":"Au Trou Gascon","promotions":[]}
{"id":"44000","name":"Logis de la Cadène","promotions":[]}
{"id":"24998","name":"Restaurant des Rois","promotions":[]}
{"id":"269931","name":"Les Jardins de l'Espadon","promotions":[]}
{"id":"3806","name":"Assiette Champenoise","promotions":[]}
{"id":"25901","name":"Hostellerie de l'Abbaye de la Celle","promotions":[]}
{"id":"8760","name":"Saturne","promotions":[]}
{"id":"60859","name":"Nakatani","promotions":[]}
{"id":"15802","name":"Cobéa","promotions":[]}
{"id":"43399","name":"La Grignotière","promotions":[]}
{"id":"351691","name":"Origine","promotions":[]}
{"id":"12900","name":"Pierre Orsi","promotions":[]}
{"id":"1310","name":"Xavier Mathieu","promotions":[]}
{"id":"689","name":"Le Prieuré","promotions":[]}
{"id":"346045","name":"Yam'Tcha","promotions":[]}
{"id":"6794","name":"Mère Brazier","promotions":[]}
{"id":"2971","name":"Maison Kieny","promotions":[]}
{"id":"10382","name":"Le Strasbourg","promotions":[]}
{"id":"2591","name":"La Table des Merville","promotions":[]}
{"id":"122","name":"La Grande Cascade","promotions":[]}
{"id":"324443","name":"Maison Clovis","promotions":[]}
{"id":"269585","name":"La Scène Thélème","promotions":[]}
{"id":"36039","name":"Hélène Darroze","promotions":[]}
{"id":"3521","name":"Le Candille","promotions":[]}
{"id":"57531","name":"La Bastide de Moustiers","promotions":[]}
{"id":"58408","name":"La Table du 11","promotions":[]}
{"id":"3592","name":"Buerehiesel","promotions":[]}
{"id":"1086","name":"Le Vivier","promotions":[]}
{"id":"326081","name":"L'Écrin","promotions":[]}
{"id":"4546","name":"Auberge des Saints Pères","promotions":[]}
{"id":"14529","name":"La Chassagnette","promotions":[]}
{"id":"6018","name":"Le Vieux Logis","promotions":[]}
{"id":"11295","name":"Qui plume la Lune","promotions":[]}
{"id":"323145","name":"Le Passe Temps","promotions":[]}
{"id":"75043","name":"Prairial","promotions":[]}
{"id":"77571","name":"La Table de Manville","promotions":[]}
{"id":"27058","name":"Initial","promotions":[]}
{"id":"344379","name":"Astrance","promotions":[]}
{"id":"60775","name":"La Table du Connétable","promotions":[]}
{"id":"9759","name":"Le Carrousel","promotions":[]}
{"id":"4294","name":"La Maison dans le Parc","promotions":[]}
{"id":"25985","name":"Copenhague","promotions":[]}
{"id":"324473","name":"Faventia","promotions":[]}
{"id":"32584","name":"L'Auberge de la Pomme","promotions":[]}
{"id":"25985","name":"Copenhague","promotions":[]}
{"id":"4546","name":"Auberge des Saints Pères","promotions":[]}
{"id":"58408","name":"La Table du 11","promotions":[]}
{"id":"6482","name":"Vieux Pont","promotions":[]}
{"id":"27058","name":"Initial","promotions":[]}
{"id":"206163","name":"Julien Binz","promotions":[]}
{"id":"60775","name":"La Table du Connétable","promotions":[]}
{"id":"6018","name":"Le Vieux Logis","promotions":[]}
{"id":"324473","name":"Faventia","promotions":[]}
{"id":"5727","name":"Mavrommatis","promotions":[]}
{"id":"7130","name":"Le Clos des Sens","promotions":[]}
{"id":"35732","name":"Anne de Bretagne","promotions":[]}
{"id":"32584","name":"L'Auberge de la Pomme","promotions":[]}
{"id":"5497","name":"La Scène","promotions":[]}
{"id":"12601","name":"Le Cerf","promotions":[]}
{"id":"21095","name":"Jérémy Galvan","promotions":[]}
{"id":"22878","name":"Domaine de Clairefontaine","promotions":[]}
{"id":"63173","name":"Fontevraud Le Restaurant","promotions":[]}
{"id":"9228","name":"Le Baudelaire","promotions":[]}
{"id":"75043","name":"Prairial","promotions":[]}
{"id":"7876","name":"Mon Plaisir","promotions":[]}
{"id":"2579","name":"Auberge de la Charme","promotions":[]}
{"id":"713","name":"L'Arôme","promotions":[]}
{"id":"18939","name":"Le Bistro des Saveurs","promotions":[]}
{"id":"19211","name":"1741","promotions":[]}
{"id":"28557","name":"La Grange de Belle-Église","promotions":[]}
{"id":"30379","name":"Jin","promotions":[]}
{"id":"330375","name":"Le Village","promotions":[]}
{"id":"61705","name":"Le Camélia","promotions":[]}
{"id":"69375","name":"Au Trou Gascon","promotions":[]}
{"id":"310829","name":"Dominique Bouchet","promotions":[]}
{"id":"28453","name":"1217","promotions":[]}
{"id":"2740","name":"Le Manoir du Lys","promotions":[]}
{"id":"46885","name":"Le Gambetta","promotions":[]}
{"id":"269053","name":"Ze Kitchen Galerie","promotions":[]}
{"id":"42187","name":"La Promenade","promotions":[]}
{"id":"2970","name":"La Renaissance","promotions":[]}
{"id":"529","name":"Le Puits du Trésor","promotions":[]}
{"id":"8760","name":"Saturne","promotions":[]}
{"id":"4904","name":"Hostellerie de Plaisance","promotions":[]}
{"id":"46990","name":"Rackham","promotions":[]}
{"id":"6710","name":"Les Rosiers","promotions":[]}
{"id":"346045","name":"Yam'Tcha","promotions":[]}
{"id":"341313","name":"Stéphane Tournié - Les Jardins de l'Opéra","promotions":[]}
{"id":"60418","name":"Apicius","promotions":[]}
{"id":"53038","name":"Le Gabriel","promotions":[]}
{"id":"324425","name":"Le Neuvième Art","promotions":[]}
{"id":"35146","name":"L'Atelier de Joël Robuchon - Étoile","promotions":[]}
{"id":"77613","name":"Meurin","promotions":[]}
{"id":"8838","name":"Henri et Joseph","promotions":[]}
{"id":"38155","name":"Flaveur","promotions":[]}
{"id":"269931","name":"Les Jardins de l'Espadon","promotions":[]}
{"id":"405","name":"Maison Rostang","promotions":[]}
{"id":"30143","name":"L'Atelier de Joël Robuchon - St-Germain","promotions":[]}
{"id":"2889","name":"La Marande","promotions":[]}
{"id":"11743","name":"Brikéténia","promotions":[]}
{"id":"23255","name":"Auberge de la Tour","promotions":[]}
{"id":"8933","name":"Les Clefs d'Argent","promotions":[]}
{"id":"5756","name":"Palm Beach","promotions":[]}
{"id":"12792","name":"La Côte Saint-Jacques","promotions":[]}
{"id":"3552","name":"Maison Lameloise","promotions":[]}
{"id":"26494","name":"La Barbacane","promotions":[]}
{"id":"351691","name":"Origine","promotions":[]}
{"id":"10889","name":"Septime","promotions":[]}
{"id":"69372","name":"Carré des Feuillants","promotions":[]}
{"id":"3806","name":"Assiette Champenoise","promotions":[]}
{"id":"5109","name":"Le Magasin aux Vivres","promotions":[]}
{"id":"294745","name":"Le Fanal","promotions":[]}
{"id":"73740","name":"La Rotonde","promotions":[]}
{"id":"3157","name":"Gill","promotions":[]}
{"id":"44919","name":"Miraflores","promotions":[]}
{"id":"6437","name":"L'Atelier du Peintre","promotions":[]}
{"id":"3507","name":"Hostellerie de Levernois","promotions":[]}
{"id":"3401","name":"Le Bec au Cauchois","promotions":[]}
{"id":"2698","name":"Jean-Luc Tartarin","promotions":[]}
{"id":"4961","name":"Ar Men Du","promotions":[]}
{"id":"73961","name":"Le George","promotions":[]}
{"id":"30315","name":"Les Climats","promotions":[]}
{"id":"1226","name":"Le Figuier de St-Esprit","promotions":[]}
{"id":"7715","name":"Terre-Mer","promotions":[]}
{"id":"9611","name":"Radio","promotions":[]}
{"id":"31008","name":"Alcyone","promotions":[]}
{"id":"2755","name":"Auberge de Clochemerle","promotions":[]}
{"id":"205419","name":"La Dame de Pic","promotions":[]}
{"id":"2998","name":"Christopher Coutanceau","promotions":[]}
{"id":"4697","name":"Les Terrasses de Lyon","promotions":[]}
{"id":"43399","name":"La Grignotière","promotions":[]}
{"id":"327881","name":"La Matelote","promotions":[]}
{"id":"22504","name":"L'Épuisette","promotions":[]}
{"id":"201032","name":"1920","promotions":[]}
{"id":"5609","name":"Chapelle Saint-Martin","promotions":[]}
{"id":"15802","name":"Cobéa","promotions":[]}
{"id":"38024","name":"La Nouvelle Auberge","promotions":[]}
{"id":"18188","name":"Le Pressoir","promotions":[]}
{"id":"65607","name":"Le Château de Sable","promotions":[]}
{"id":"301377","name":"Le Chantecler","promotions":[]}
{"id":"74933","name":"Le Clarence","promotions":[]}
{"id":"26660","name":"La Vague d'Or","promotions":[]}
{"id":"23303","name":"La Table de Nans","promotions":[]}
{"id":"214579","name":"L'Arcane","promotions":[]}
{"id":"128","name":"Hervé Busset","promotions":[]}
{"id":"221","name":"Le France","promotions":[]}
{"id":"366063","name":"Château Cordeillan-Bages","promotions":[]}
{"id":"10382","name":"Le Strasbourg","promotions":[]}
{"id":"25896","name":"Benoit","promotions":[]}
{"id":"200546","name":"Sylvestre","promotions":[]}
{"id":"25901","name":"Hostellerie de l'Abbaye de la Celle","promotions":[]}
{"id":"77626","name":"Alliance","promotions":[]}
{"id":"15068","name":"Au Vieux Couvent","promotions":[]}
{"id":"277471","name":"Alain Llorca","promotions":[]}
{"id":"12900","name":"Pierre Orsi","promotions":[]}
{"id":"204609","name":"Le Castellaras","promotions":[]}
{"id":"32118","name":"Le Musigny","promotions":[]}
{"id":"289175","name":"La Grande Maison de Bernard Magrez","promotions":[]}
{"id":"68308","name":"Thierry Drapeau","promotions":[]}
{"id":"36448","name":"Penati al Baretto","promotions":[]}
{"id":"79692","name":"Assa","promotions":[]}
{"id":"3485","name":"Manoir de la Boulaie","promotions":[]}
{"id":"15418","name":"Les Loges","promotions":[]}
{"id":"291337","name":"Épicure","promotions":[]}
{"id":"6986","name":"Alexandre","promotions":[]}
{"id":"785","name":"Lucas Carton","promotions":[]}
{"id":"8977","name":"Shang Palace","promotions":[]}
{"id":"1009","name":"Domaine des Séquoias","promotions":[]}
{"id":"7872","name":"Le Pavillon des Boulevards","promotions":[]}
{"id":"5649","name":"La Grand'Vigne","promotions":[]}
{"id":"60777","name":"1912","promotions":[]}
{"id":"23454","name":"Helen","promotions":[]}
{"id":"953","name":"La Bonne Étape","promotions":[]}
{"id":"687","name":"L'Oustau de Baumanière","promotions":[]}
{"id":"5020","name":"La Fourchette du Printemps","promotions":[]}
{"id":"14529","name":"La Chassagnette","promotions":[]}
{"id":"3592","name":"Buerehiesel","promotions":[]}
{"id":"323145","name":"Le Passe Temps","promotions":[]}
{"id":"344379","name":"Astrance","promotions":[]}
{"id":"326081","name":"L'Écrin","promotions":[]}
{"id":"1086","name":"Le Vivier","promotions":[]}
{"id":"33786","name":"Le 1947","promotions":[]}
{"id":"11295","name":"Qui plume la Lune","promotions":[]}
{"id":"4294","name":"La Maison dans le Parc","promotions":[]}
{"id":"24998","name":"Restaurant des Rois","promotions":[]}
{"id":"10427","name":"Les Morainières","promotions":[]}
{"id":"5632","name":"La Licorne Royale","promotions":[]}
{"id":"77571","name":"La Table de Manville","promotions":[]}
{"id":"9759","name":"Le Carrousel","promotions":[]}
{"id":"26327","name":"Elsa","promotions":[]}
{"id":"60859","name":"Nakatani","promotions":[]}
{"id":"209193","name":"Ed.Em","promotions":[]}
{"id":"7135","name":"Les Trois Rochers","promotions":[]}
{"id":"682","name":"L'Oasis","promotions":[]}
{"id":"29826","name":"Loiseau des Ducs","promotions":[]}
{"id":"25","name":"Loiseau rive Gauche","promotions":[]}
{"id":"337449","name":"Comice","promotions":[]}
{"id":"276169","name":"Ken Kawasaki","promotions":[]}
{"id":"2185","name":"Antoine","promotions":[]}
{"id":"317277","name":"Quinsou","promotions":[]}
{"id":"5623","name":"Le Corot","promotions":[]}
{"id":"7784","name":"Auberge St-Walfrid","promotions":[]}
{"id":"202436","name":"Le Chateaubriand","promotions":[]}
{"id":"287357","name":"La Palme d'Or","promotions":[]}
{"id":"284489","name":"L'Archeste","promotions":[]}
{"id":"347931","name":"SEPT","promotions":[]}
{"id":"6448","name":"Les Bacchanales","promotions":[]}
{"id":"21741","name":"Restaurant du Palais Royal","promotions":[]}
{"id":"16314","name":"Les Fresques","promotions":[]}
{"id":"71542","name":"Au Crocodile","promotions":[]}
{"id":"313905","name":"Auberge Le Prieuré","promotions":[]}
{"id":"269585","name":"La Scène Thélème","promotions":[]}
{"id":"1310","name":"Xavier Mathieu","promotions":[]}
{"id":"21632","name":"L'Essentiel","promotions":[]}
{"id":"18271","name":"Le Clair de la Plume","promotions":[]}
{"id":"13311","name":"Château de Mercuès","promotions":[]}
{"id":"44000","name":"Logis de la Cadène","promotions":[]}
{"id":"209577","name":"Restaurant H","promotions":[]}
{"id":"3521","name":"Le Candille","promotions":[]}
{"id":"272593","name":"Montée","promotions":[]}
{"id":"8719","name":"Ô Saveurs","promotions":[]}
{"id":"8976","name":"L'Abeille","promotions":[]}
{"id":"36039","name":"Hélène Darroze","promotions":[]}
{"id":"276775","name":"Garopapilles","promotions":[]}
{"id":"4977","name":"Le Saint-James","promotions":[]}
{"id":"291883","name":"La Table de l'Alpaga","promotions":[]}
{"id":"36884","name":"La Table d'Eugène","promotions":[]}
{"id":"8628","name":"Le Park 45","promotions":[]}
{"id":"31795","name":"Auberge du Vert Mont","promotions":[]}
{"id":"689","name":"Le Prieuré","promotions":[]}
{"id":"203823","name":"La Passagère","promotions":[]}
{"id":"78533","name":"Le Quincangrogne","promotions":[]}
{"id":"3997","name":"Têtedoie","promotions":[]}
{"id":"2975","name":"La Table du Gourmet","promotions":[]}
{"id":"275","name":"Le Meurice Alain Ducasse","promotions":[]}
{"id":"306505","name":"Le Pavillon","promotions":[]}
{"id":"2591","name":"La Table des Merville","promotions":[]}
{"id":"2310","name":"Auberge du Cheval Blanc","promotions":[]}
{"id":"53046","name":"Sur Mesure par Thierry Marx","promotions":[]}
{"id":"11050","name":"Le Cloître","promotions":[]}
{"id":"26201","name":"Auguste","promotions":[]}
{"id":"26352","name":"Le Moulin de l'Abbaye","promotions":[]}
{"id":"2828","name":"Le Chiberta","promotions":[]}
{"id":"5487","name":"Château de Mirambeau","promotions":[]}
{"id":"2728","name":"L'Orangerie du Château","promotions":[]}
{"id":"15413","name":"Les Trois Dômes","promotions":[]}
{"id":"77571","name":"La Table de Manville","promotions":[]}
{"id":"713","name":"L'Arôme","promotions":[]}
{"id":"269053","name":"Ze Kitchen Galerie","promotions":[]}
{"id":"46885","name":"Le Gambetta","promotions":[]}
{"id":"344379","name":"Astrance","promotions":[]}
{"id":"1086","name":"Le Vivier","promotions":[]}
{"id":"2975","name":"La Table du Gourmet","promotions":[]}
{"id":"24272","name":"St-James Paris","promotions":[]}
{"id":"2819","name":"Les Hautes Roches","promotions":[]}
{"id":"2591","name":"La Table des Merville","promotions":[]}
{"id":"3303","name":"Le Relais Bernard Loiseau","promotions":[]}
{"id":"3931","name":"William Frachot","promotions":[]}
{"id":"8838","name":"Henri et Joseph","promotions":[]}
{"id":"3157","name":"Gill","promotions":[]}
{"id":"324425","name":"Le Neuvième Art","promotions":[]}
{"id":"201032","name":"1920","promotions":[]}
{"id":"16314","name":"Les Fresques","promotions":[]}
{"id":"7784","name":"Auberge St-Walfrid","promotions":[]}
{"id":"25701","name":"Garance","promotions":[]}
{"id":"272053","name":"Divellec","promotions":[]}
{"id":"26201","name":"Auguste","promotions":[]}
{"id":"5756","name":"Palm Beach","promotions":[]}
{"id":"306505","name":"Le Pavillon","promotions":[]}
